iamx/__init__.py
iamx/cli.py
iamx/core/analyzer.py
iamx/core/models.py
iamx/core/parser.py
iamx/reports/__init__.py
iamx/reports/json.py
iamx/reports/markdown.py
iamx/rules/__init__.py
iamx/rules/base.py
iamx/rules/permissions.py
iamx/rules/resources.py
iamx/web/app_fixed.py
iamx-0.1.0.dist-info/METADATA
iamx-0.1.0.dist-info/WHEEL
iamx-0.1.0.dist-info/entry_points.txt
iamx-0.1.0.dist-info/licenses/LICENSE
iamx-0.1.0.dist-info/RECORD
