Metadata-Version: 2.4
Name: iamx
Version: 0.1.0
Summary: IAM Policy Explainer - Local-first IAM policy analyzer with deterministic risk detection
Project-URL: Homepage, https://github.com/iamsteve0/iamx
Project-URL: Documentation, https://github.com/iamsteve0/iamx#readme
Project-URL: Repository, https://github.com/iamsteve0/iamx
Project-URL: Issues, https://github.com/iamsteve0/iamx/issues
Author-email: iamsteve0 <sefthuko28.projects@gmail.com>
License: MIT
License-File: LICENSE
Keywords: analyzer,aws,devops,iam,policy,security
Classifier: Development Status :: 3 - Alpha
Classifier: Intended Audience :: Developers
Classifier: Intended Audience :: System Administrators
Classifier: License :: OSI Approved :: MIT License
Classifier: Operating System :: OS Independent
Classifier: Programming Language :: Python :: 3
Classifier: Programming Language :: Python :: 3.8
Classifier: Programming Language :: Python :: 3.9
Classifier: Programming Language :: Python :: 3.10
Classifier: Programming Language :: Python :: 3.11
Classifier: Programming Language :: Python :: 3.12
Classifier: Topic :: Security
Classifier: Topic :: Software Development :: Libraries :: Python Modules
Classifier: Topic :: System :: Systems Administration
Requires-Python: >=3.8
Requires-Dist: boto3>=1.26.0
Requires-Dist: botocore>=1.29.0
Requires-Dist: click>=8.0.0
Requires-Dist: fastapi>=0.100.0
Requires-Dist: jinja2>=3.0.0
Requires-Dist: pydantic>=2.0.0
Requires-Dist: python-multipart>=0.0.20
Requires-Dist: pyyaml>=6.0
Requires-Dist: rich>=13.0.0
Requires-Dist: uvicorn[standard]>=0.20.0
Provides-Extra: dev
Requires-Dist: black>=23.0.0; extra == 'dev'
Requires-Dist: flake8>=6.0.0; extra == 'dev'
Requires-Dist: mypy>=1.0.0; extra == 'dev'
Requires-Dist: pre-commit>=3.0.0; extra == 'dev'
Requires-Dist: pytest-cov>=4.0.0; extra == 'dev'
Requires-Dist: pytest>=7.0.0; extra == 'dev'
Requires-Dist: tox>=4.0.0; extra == 'dev'
Provides-Extra: web
Requires-Dist: fastapi>=0.100.0; extra == 'web'
Requires-Dist: jinja2>=3.0.0; extra == 'web'
Requires-Dist: uvicorn[standard]>=0.20.0; extra == 'web'
